{"type": "FeatureCollection","crs": { "type": "name", "properties": { "name": "urn:ogc:def:crs:OGC:1.3:CRS84" } },
"features": [{ "type": "Feature", "properties": { "HID": 1001, "Type": "認可保育所", "Kodomo": null, "Name": "城東保育所", "Label": "城東保育所", "AgeS": "57日", "AgeE": "就学前", "Full": "120", "Open": "7:00", "Close": "18:00", "H24": null, "Memo": null, "Extra": "1", "Temp": null, "Holiday": null, "Night": null, "Add1": "松江市", "Add2": "学園一丁目10-12", "TEL": "0852-21-2587", "FAX": null, "Owner": null, "Ownership": "公", "Proof": null, "Shanai": null, "Y": 35.47951700, "X": 133.06725000, "url": null, "Vacancy": null, "VacancyDate": null }, "geometry": { "type": "Point", "coordinates": [ 133.06725000, 35.47951700 ] } },
{ "type": "Feature", "properties": { "HID": 1002, "Type": "認可保育所", "Kodomo": null, "Name": "たまち保育園", "Label": "たまち保育園", "AgeS": "43日", "AgeE": "就学前", "Full": "170", "Open": "7:00", "Close": "18:00", "H24": null, "Memo": null, "Extra": "1", "Temp": "Y", "Holiday": null, "Night": null, "Add1": "松江市", "Add2": "西川津町1610-4", "TEL": "0852-26-5454", "FAX": null, "Owner": null, "Ownership": "私", "Proof": null, "Shanai": null, "Y": 35.47104600, "X": 133.07097200, "url": "http:\/\/tamachi-matsue.jp\/tamachi\/", "Vacancy": null, "VacancyDate": null }, "geometry": { "type": "Point", "coordinates": [ 133.07097200, 35.47104600 ] } },
{ "type": "Feature", "properties": { "HID": 1003, "Type": "認可保育所", "Kodomo": null, "Name": "たまち乳児保育園", "Label": "たまち乳児保育園", "AgeS": "43日", "AgeE": "2歳", "Full": "90", "Open": "7:00", "Close": "18:00", "H24": null, "Memo": "3歳になる年度末までの保育所です。希望する方は翌年度全員たまち保育園に移ることができます。", "Extra": "1", "Temp": null, "Holiday": null, "Night": null, "Add1": "松江市", "Add2": "西川津町1610-2", "TEL": "0852-60-1160", "FAX": null, "Owner": null, "Ownership": "私", "Proof": null, "Shanai": null, "Y": 35.47111200, "X": 133.07142200, "url": "http:\/\/tamachi-matsue.jp\/nyuji\/", "Vacancy": null, "VacancyDate": null }, "geometry": { "type": "Point", "coordinates": [ 133.07142200, 35.47111200 ] } }]}
